c7n_logexporter/__init__.py
c7n_logexporter/exporter.py
c7n_logexporter/flowdeliver.py
c7n_logexporter/stream.py
c7n_logexporter-0.4.44.dist-info/WHEEL
c7n_logexporter-0.4.44.dist-info/entry_points.txt
c7n_logexporter-0.4.44.dist-info/RECORD
c7n_logexporter-0.4.44.dist-info/METADATA
